retry_requests/__init__.py
retry_requests-2.0.0.dist-info/LICENSE
retry_requests-2.0.0.dist-info/METADATA
retry_requests-2.0.0.dist-info/WHEEL
retry_requests-2.0.0.dist-info/top_level.txt
retry_requests-2.0.0.dist-info/RECORD
