Metadata-Version: 2.1
Name: retry-requests
Version: 2.0.0
Summary: Make requests's sessions auto-retry on failure.
Home-page: https://github.com/bustawin/retry-requests
Author: Xavier Bustamante Talavera
Author-email: xavier@bustawin.com
License: GPLv3+
Project-URL: Documentation, https://github.com/bustawin/retry-requests
Project-URL: Code, https://github.com/bustawin/retry-requests
Project-URL: Issue tracker, https://github.com/bustawin/retry-requests/issues
Classifier: Development Status :: 5 - Production/Stable
Classifier: Intended Audience :: Developers
Classifier: Operating System :: OS Independent
Classifier: License :: OSI Approved :: GNU General Public License v3 or later (GPLv3+)
Classifier: Programming Language :: Python :: 3 :: Only
Classifier: Programming Language :: Python :: 3.6
Classifier: Programming Language :: Python :: 3.7
Classifier: Programming Language :: Python :: 3.8
Classifier: Topic :: Software Development :: Libraries :: Python Modules
Requires-Python: >=3.6
Provides-Extra: test
License-File: LICENSE
